strabs/deploy/__init__.py
strabs/deploy/confirm.py
strabs/deploy/env.py
strabs/deploy/git.py
strabs/deploy/helm.py
strabs/deploy/juggernaut.py
strabs/deploy/kapp.py
strabs/deploy/kube.py
strabs/deploy/kubie.py
strabs/deploy/localdev.py
strabs/deploy/talos.py
strabs_deploy-0.1.3.dist-info/METADATA
strabs_deploy-0.1.3.dist-info/WHEEL
strabs_deploy-0.1.3.dist-info/RECORD
