Metadata-Version: 2.4
Name: strabs-deploy
Version: 0.1.3
Summary: Kubernetes deployment utilities
Requires-Python: >=3.10
Requires-Dist: invoke
Requires-Dist: pyyaml
Requires-Dist: rich
Requires-Dist: strabs-doit>=0.1.3
Provides-Extra: dev
Requires-Dist: mypy>=1.19; extra == 'dev'
Requires-Dist: pytest>=9.0; extra == 'dev'
Requires-Dist: ruff>=0.14; extra == 'dev'
Requires-Dist: types-pyyaml; extra == 'dev'
